Workbook

Sheet Soutenance et Prototype
A1: Grille évaluation Option Prototypage - Soutenance et Prototype
A2: NOM - Prénom :
A3: Evaluateurs :
A5: Critères | B5: 5 pts | C5: 4 pts | D5: 2 pts | E5: 1 pt | F5: Coeff | G5: Score
A6: Qualité du prototype | B6: Le prototype est fonctionnel dans son ensemble | C6: Seule la fonctione essentielle du prototype est opérationnelle | D6: Le prototype est non fonctionnel | E6: Il n'y a pas de prototype | F6: 5 | H6: =G6*F6 -> 0
A7: Démarche d’ingénierie | B7: Identification des contraintes, validation technique, choix technologiques justifiés. Tests, ajustements, retour sur expérience, résolution de problèmes. | C7: Démarche simple | D7: Des écarts mineurs | E7: Pas de démarche | F7: 5 | H7: =G7*F7 -> 0
A8: Management de projet | B8: Mise en place d'outils et méthodes de gestion de projet pertinent et efficace | C8: Quelques outils mis en place mais pas toujours suivi | D8: Pas d'outils mis en place | E8: Aucunes méthodes, le projet n'est pas suivi mais subit | F8: 4 | H8: =G8*F8 -> 0
A9: Programmation informatique | B9: La programmation est pertinente et apporte un réel intérêt. La programmation est fonctionnelle La programmation est réfléchit et optimisée | C9: La programmation est fonctionnelle La programmation reste basique | D9: La programmation n'est pas maîtirisée | E9: Pas de programmation | F9: 2 | H9: =G9*F9 -> 0
A10: Modélisation 3D | B10: La conception 3D est pertinente et apporte un vrai intérêt fonctionnel | C10: Modélisation esthétique | D10: La conception 3D n'est pas originale Récupération de modèle existant et modifications mineures. | E10: Pas de modélisation 3D | F10: 2 | H10: =G10*F10 -> 0
A11: Gestion budgétaire | B11: L'ensemble des coûts du projet sont identifiés : - coût matériel du prototype final - coût matériel des différentes itérations - Coût des pièces non exploitées - Temps de développement | C11: Certains coûts ne sont pas présentés | D11: Des écarts mineurs | E11: Des écarts importants | F11: 2 | H11: =G11*F11 -> 0
A12: Réparabilité | B12: Une réflexion sur la fin de vie du produit est proposée. Le choix des matériaux est réfléchi Les commandes de matériel ont été réfléchies Le projet est démontable / réparable facilement. | C12: Pas de réflexion sur la fin de vie. Les commandes de matériel n'ont pas été pertinentes | D12: Démarche faible - prototype non réparable | E12: Pas de démarche | F12: 2 | H12: =G12*F12 -> 0
A13: Maitrise et rigueur technique | B13: L'étudiant démontre une maitrise de l'ensemble des technologies mises en œuvre | C13: L'étudiant démontre une maîtrise partielle | D13: L'étudiants ne maîtrise pas les éléments non essentiel à son projet | E13: Aucune maîtrise | F13: 2 | H13: =G13*F13 -> 0
A14: Présentation | B14: Structure, clarté, langage technique, gestion du temps. Support de qualité professionnelle Présentation Dynamique | C14: Quelques fautes dans le support Présentation manquant de dynamisme | D14: Plus de 5 fautes dans le support Manque de préparation | E14: Soutenance non préparée | F14: 2 | H14: =G14*F14 -> 0
A15: Moyenne | F15: =SUM(F6:F14) -> 26 | G15: =H15/F15 -> 0 | H15: =SUM(H6:H14) -> 0
A16: Evaluation | G16: =IF(G15=0,"",IF(G15>=4.6,"A",IF(G15>=3.6,"B",IF(G15<1.6,"D","C"))))
A18: Commentaires

Sheet Rapport
A1: Grille évaluation Option Prototypage - Rapport
A2: NOM - Prénom : | B2: ='Soutenance et Prototype'!B2 -> 0
A3: Evaluateurs :
A5: Critères | B5: 5 pts | C5: 4 pts | D5: 2 pts | E5: 1 pt | F5: Coeff | G5: Score
A6: Cahier des charges et analyse fonctionnelle | B6: Cahier des charges complet, clair, structuré. Analyse fonctionnelle détaillée et justifiée. | C6: CDC clair et cohérent, analyse fonctionnelle correcte mais partielle. | D6: CDC incomplet ou peu structuré. Analyse fonctionnelle superficielle. | E6: CDC très incomplet ou absent. Analyse fonctionnelle erronée. | F6: 4 | H6: =G6*F6 -> 0
A7: Dossier technique – Étapes de réalisation | B7: Étapes complètes et précises (modélisation, fabrication, tests). Visuels professionnels. Archives complètes | C7: Bon niveau de détail, quelques étapes moins documentées. | D7: Documentation insuffisante ou non chronologique. | E7: Documentation très faible ou inexistante. | F7: 4 | H7: =G7*F7 -> 0
A8: Tracé des choix techniques | B8: Justification détaillée, alternatives étudiées, cohérence avec CDC. | C8: Justification correcte mais partielle. | D8: Justifications superficielles ou techniques peu adaptées. | E8: Aucune justification des choix. | F8: 2 | H8: =G8*F8 -> 0
A9: Management de projet et outils | B9: Usage complet d’outils (Kanban, budget, risques, MVP…). Analyse critique. | C9: Outils utilisés mais analyse limitée. | D9: Usage minimal ou irrégulier. | E9: Absence d’outils de gestion. | F9: 4 | H9: =G9*F9 -> 0
A10: Cohérence objectifs / résultats | B10: Alignement parfait + analyse claire des écarts. | C10: Bonne cohérence générale. | D10: Plusieurs incohérences non justifiées. | E10: Manque de cohérence global. | F10: 2 | H10: =G10*F10 -> 0
A11: Qualité professionnelle du document | B11: Document structuré, soigné, sans fautes. Mise en page pro. | C11: Document clair, quelques erreurs mineures. | D11: Document brouillon ou peu structuré. | E11: Document difficile à lire, fautes majeures. | F11: 2 | H11: =G11*F11 -> 0
A12: Analyse réflexive | B12: Analyse approfondie des réussites, difficultés, améliorations. | C12: Bonne analyse mais moins approfondie. | D12: Analyse superficielle, descriptive. | E12: Aucune analyse réflexive. | F12: 2 | H12: =G12*F12 -> 0
A13: Moyenne | F13: =SUM(F6:F12) -> 20 | G13: =H13/F13 -> 0 | H13: =SUM(H6:H12) -> 0
A14: Evaluation | G14: =IF(G13=0,"",IF(G13>=4.6,"A",IF(G13>=3.6,"B",IF(G13<1.6,"D","C"))))
A16: Commentaires

Sheet Implication
A1: Grille évaluation Option Prototypage - Implication
A2: NOM - Prénom : | B2: ='Soutenance et Prototype'!B2 -> 0
A3: Evaluateurs :
A5: Critères | B5: 5 pts | C5: 4 pts | D5: 2 pts | E5: 1 pt | F5: Coeff | G5: Score
A6: Implication et engagement personnel | B6: Très fort investissement : initiative, motivation constante, travail approfondi. | C6: Engagement sérieux et régulier, bonne autonomie. | D6: Engagement variable, travail minimal ou irrégulier. | E6: Faible engagement, travail insuffisant. | F6: 2 | H6: =G6*F6 -> 0
A7: Assiduité et ponctualité | B7: Présence irréprochable, aucune absence injustifiée, ponctualité constante. | C7: Bonne assiduité, quelques retards ou absences mineures. (Absences justifiées ou moins de 4 retards) | D7: Assiduité irrégulière, retards répétés ou absences non justifiées. (5 retards) | E7: Absences fréquentes, participation insuffisante. (6 retards) | F7: 2 | H7: =G7*F7 -> 0
A8: Respect des échéances | B8: Toutes les échéances respectées ou rendues en avance, travail complet. | C8: Majorité des échéances respectées, retards mineurs. | D8: Plusieurs livrables en retard ou incomplets. | E8: Livrables très en retard ou non rendus. | F8: 2 | H8: =G8*F8 -> 0
A9: Professionnalisme (autonomie, rigueur, attitude) | B9: Travail rigoureux, autonomie élevée, attitude professionnelle constante. | C9: Travail sérieux et rigoureux, autonomie satisfaisante. | D9: Manque de rigueur ou autonomie irrégulière. | E9: Attitude non professionnelle, manque de sérieux. | F9: 2 | H9: =G9*F9 -> 0
A10: Communication | B10: Communication proactive et régulière, questions pertinentes. | C10: Communication claire et conforme aux attentes. | D10: Communication limitée ou tardive. | E10: Communication absente, ne rend pas compte du travail. | F10: 2 | H10: =G10*F10 -> 0
A11: Moyenne | F11: =SUM(F6:F10) -> 10 | G11: =H11/F11 -> 0 | H11: =SUM(H6:H10) -> 0
A12: Evaluation | G12: =IF(G11=0,"",IF(G11>=4.6,"A",IF(G11>=3.6,"B",IF(G11<1.6,"D","C"))))
A14: Commentaires

Sheet Synthèse Scholaris
A1: Grille évaluation Option Prototypage - Implication
A2: NOM - Prénom : | B2: ='Soutenance et Prototype'!B2 -> 0
A3: Evaluateurs :
A5: UE Option | B5: Note
A6: Option : Compétences | B6: =Rapport!G14
A7: Option : Réalisation | B7: ='Soutenance et Prototype'!G16
A8: Option : Evaluation par les pairs | B8: =Implication!G12
